<annotation verified="yes">
	<folder>028-nepal, Kathmandu-march08-sagar</folder>
	<filename>IMG_20200308_151734_1.jpg</filename>
	<path>/028-nepal, Kathmandu-march08-sagar/IMG_20200308_151734_1.jpg</path>
	<source>
		<database>Unknown</database>
	</source>
	<size>
		<width>3024</width>
		<height>4032</height>
		<depth>3</depth>
	</size>
	<segmented>0</segmented>
	<object>
		<name>Plastic Bottle</name>
		<pose>Unspecified</pose>
		<truncated>1</truncated>
		<difficult>0</difficult>
		<bndbox>
			<xmin>676</xmin>
			<ymin>3934</ymin>
			<xmax>817</xmax>
			<ymax>4032</ymax>
		</bndbox>
	</object>
	<object>
		<name>Plastic Bottle</name>
		<pose>Unspecified</pose>
		<truncated>0</truncated>
		<difficult>0</difficult>
		<bndbox>
			<xmin>283</xmin>
			<ymin>2852</ymin>
			<xmax>370</xmax>
			<ymax>2947</ymax>
		</bndbox>
	</object>
	<object>
		<name>Plastic Bottle</name>
		<pose>Unspecified</pose>
		<truncated>0</truncated>
		<difficult>0</difficult>
		<bndbox>
			<xmin>295</xmin>
			<ymin>2757</ymin>
			<xmax>396</xmax>
			<ymax>2851</ymax>
		</bndbox>
	</object>
	<object>
		<name>Plastic Bottle</name>
		<pose>Unspecified</pose>
		<truncated>0</truncated>
		<difficult>0</difficult>
		<bndbox>
			<xmin>854</xmin>
			<ymin>2197</ymin>
			<xmax>945</xmax>
			<ymax>2277</ymax>
		</bndbox>
	</object>
	<object>
		<name>Plastic Bottle</name>
		<pose>Unspecified</pose>
		<truncated>0</truncated>
		<difficult>0</difficult>
		<bndbox>
			<xmin>2513</xmin>
			<ymin>2119</ymin>
			<xmax>2565</xmax>
			<ymax>2149</ymax>
		</bndbox>
	</object>
	<object>
		<name>Plastic Bottle</name>
		<pose>Unspecified</pose>
		<truncated>0</truncated>
		<difficult>0</difficult>
		<bndbox>
			<xmin>1435</xmin>
			<ymin>2550</ymin>
			<xmax>1530</xmax>
			<ymax>2660</ymax>
		</bndbox>
	</object>
	<object>
		<name>Plastic Bottle</name>
		<pose>Unspecified</pose>
		<truncated>0</truncated>
		<difficult>0</difficult>
		<bndbox>
			<xmin>1442</xmin>
			<ymin>2805</ymin>
			<xmax>1558</xmax>
			<ymax>2906</ymax>
		</bndbox>
	</object>
	<object>
		<name>Plastic Bottle</name>
		<pose>Unspecified</pose>
		<truncated>0</truncated>
		<difficult>0</difficult>
		<bndbox>
			<xmin>1294</xmin>
			<ymin>2715</ymin>
			<xmax>1358</xmax>
			<ymax>2808</ymax>
		</bndbox>
	</object>
	<object>
		<name>Plastic Bottle</name>
		<pose>Unspecified</pose>
		<truncated>0</truncated>
		<difficult>0</difficult>
		<bndbox>
			<xmin>1046</xmin>
			<ymin>2678</ymin>
			<xmax>1149</xmax>
			<ymax>2743</ymax>
		</bndbox>
	</object>
</annotation>
