<annotation verified="yes">
	<folder>034-lahore-pakistan-plasticbottlepictures-ansub</folder>
	<filename>20200312_164552.jpg</filename>
	<path>/034-lahore-pakistan-plasticbottlepictures-ansub/20200312_164552.jpg</path>
	<source>
		<database>Unknown</database>
	</source>
	<size>
		<width>1440</width>
		<height>2560</height>
		<depth>3</depth>
	</size>
	<segmented>0</segmented>
	<object>
		<name>Plastic Bottle</name>
		<pose>Unspecified</pose>
		<truncated>1</truncated>
		<difficult>0</difficult>
		<bndbox>
			<xmin>1</xmin>
			<ymin>2050</ymin>
			<xmax>241</xmax>
			<ymax>2256</ymax>
		</bndbox>
	</object>
	<object>
		<name>Plastic Bottle</name>
		<pose>Unspecified</pose>
		<truncated>0</truncated>
		<difficult>0</difficult>
		<bndbox>
			<xmin>347</xmin>
			<ymin>1441</ymin>
			<xmax>509</xmax>
			<ymax>1499</ymax>
		</bndbox>
	</object>
	<object>
		<name>Plastic Bottle</name>
		<pose>Unspecified</pose>
		<truncated>0</truncated>
		<difficult>0</difficult>
		<bndbox>
			<xmin>403</xmin>
			<ymin>1358</ymin>
			<xmax>531</xmax>
			<ymax>1412</ymax>
		</bndbox>
	</object>
	<object>
		<name>Plastic Bottle</name>
		<pose>Unspecified</pose>
		<truncated>0</truncated>
		<difficult>0</difficult>
		<bndbox>
			<xmin>917</xmin>
			<ymin>1249</ymin>
			<xmax>1017</xmax>
			<ymax>1298</ymax>
		</bndbox>
	</object>
	<object>
		<name>Plastic Bottle</name>
		<pose>Unspecified</pose>
		<truncated>0</truncated>
		<difficult>0</difficult>
		<bndbox>
			<xmin>877</xmin>
			<ymin>1331</ymin>
			<xmax>965</xmax>
			<ymax>1383</ymax>
		</bndbox>
	</object>
	<object>
		<name>Plastic Bottle</name>
		<pose>Unspecified</pose>
		<truncated>0</truncated>
		<difficult>0</difficult>
		<bndbox>
			<xmin>1202</xmin>
			<ymin>1155</ymin>
			<xmax>1259</xmax>
			<ymax>1186</ymax>
		</bndbox>
	</object>
</annotation>
