<annotation>
	<folder>007-lahore-pakistan-photosofplasticbottlesinriver-ansub</folder>
	<filename>20200220_164457.jpg</filename>
	<path>/007-lahore-pakistan-photosofplasticbottlesinriver-ansub/20200220_164457.jpg</path>
	<source>
		<database>Unknown</database>
	</source>
	<size>
		<width>2560</width>
		<height>1440</height>
		<depth>3</depth>
	</size>
	<segmented>0</segmented>
	<object>
		<name>Plastic Bottle</name>
		<pose>Unspecified</pose>
		<truncated>1</truncated>
		<difficult>0</difficult>
		<bndbox>
			<xmin>1877</xmin>
			<ymin>1353</ymin>
			<xmax>1962</xmax>
			<ymax>1440</ymax>
		</bndbox>
	</object>
	<object>
		<name>Plastic Bottle</name>
		<pose>Unspecified</pose>
		<truncated>0</truncated>
		<difficult>0</difficult>
		<bndbox>
			<xmin>1646</xmin>
			<ymin>605</ymin>
			<xmax>1729</xmax>
			<ymax>832</ymax>
		</bndbox>
	</object>
	<object>
		<name>Plastic Bottle</name>
		<pose>Unspecified</pose>
		<truncated>0</truncated>
		<difficult>0</difficult>
		<bndbox>
			<xmin>1684</xmin>
			<ymin>735</ymin>
			<xmax>1781</xmax>
			<ymax>793</ymax>
		</bndbox>
	</object>
	<object>
		<name>Plastic Bottle</name>
		<pose>Unspecified</pose>
		<truncated>0</truncated>
		<difficult>0</difficult>
		<bndbox>
			<xmin>1496</xmin>
			<ymin>354</ymin>
			<xmax>1603</xmax>
			<ymax>441</ymax>
		</bndbox>
	</object>
	<object>
		<name>Plastic Bottle</name>
		<pose>Unspecified</pose>
		<truncated>0</truncated>
		<difficult>0</difficult>
		<bndbox>
			<xmin>1555</xmin>
			<ymin>442</ymin>
			<xmax>1654</xmax>
			<ymax>538</ymax>
		</bndbox>
	</object>
	<object>
		<name>Plastic Bottle</name>
		<pose>Unspecified</pose>
		<truncated>0</truncated>
		<difficult>0</difficult>
		<bndbox>
			<xmin>1529</xmin>
			<ymin>466</ymin>
			<xmax>1573</xmax>
			<ymax>565</ymax>
		</bndbox>
	</object>
	<object>
		<name>Plastic Bottle</name>
		<pose>Unspecified</pose>
		<truncated>0</truncated>
		<difficult>0</difficult>
		<bndbox>
			<xmin>1564</xmin>
			<ymin>527</ymin>
			<xmax>1685</xmax>
			<ymax>591</ymax>
		</bndbox>
	</object>
	<object>
		<name>Plastic Bottle</name>
		<pose>Unspecified</pose>
		<truncated>0</truncated>
		<difficult>0</difficult>
		<bndbox>
			<xmin>1497</xmin>
			<ymin>102</ymin>
			<xmax>1570</xmax>
			<ymax>248</ymax>
		</bndbox>
	</object>
	<object>
		<name>Plastic Bottle</name>
		<pose>Unspecified</pose>
		<truncated>0</truncated>
		<difficult>0</difficult>
		<bndbox>
			<xmin>1462</xmin>
			<ymin>22</ymin>
			<xmax>1527</xmax>
			<ymax>126</ymax>
		</bndbox>
	</object>
	<object>
		<name>Plastic Bottle</name>
		<pose>Unspecified</pose>
		<truncated>0</truncated>
		<difficult>0</difficult>
		<bndbox>
			<xmin>1442</xmin>
			<ymin>65</ymin>
			<xmax>1499</xmax>
			<ymax>186</ymax>
		</bndbox>
	</object>
	<object>
		<name>Plastic Bottle</name>
		<pose>Unspecified</pose>
		<truncated>1</truncated>
		<difficult>0</difficult>
		<bndbox>
			<xmin>1440</xmin>
			<ymin>1</ymin>
			<xmax>1495</xmax>
			<ymax>75</ymax>
		</bndbox>
	</object>
	<object>
		<name>Plastic Bottle</name>
		<pose>Unspecified</pose>
		<truncated>0</truncated>
		<difficult>0</difficult>
		<bndbox>
			<xmin>1392</xmin>
			<ymin>2</ymin>
			<xmax>1448</xmax>
			<ymax>88</ymax>
		</bndbox>
	</object>
	<object>
		<name>Plastic Bottle</name>
		<pose>Unspecified</pose>
		<truncated>1</truncated>
		<difficult>0</difficult>
		<bndbox>
			<xmin>1352</xmin>
			<ymin>1</ymin>
			<xmax>1392</xmax>
			<ymax>40</ymax>
		</bndbox>
	</object>
	<object>
		<name>Plastic Bottle</name>
		<pose>Unspecified</pose>
		<truncated>1</truncated>
		<difficult>0</difficult>
		<bndbox>
			<xmin>1388</xmin>
			<ymin>1</ymin>
			<xmax>1416</xmax>
			<ymax>57</ymax>
		</bndbox>
	</object>
</annotation>
