<annotation verified="yes">
	<folder>007-lahore-pakistan-photosofplasticbottlesinriver-ansub</folder>
	<filename>20200220_164942.jpg</filename>
	<path>/007-lahore-pakistan-photosofplasticbottlesinriver-ansub/20200220_164942.jpg</path>
	<source>
		<database>Unknown</database>
	</source>
	<size>
		<width>2560</width>
		<height>1440</height>
		<depth>3</depth>
	</size>
	<segmented>0</segmented>
	<object>
		<name>Plastic Bottle</name>
		<pose>Unspecified</pose>
		<truncated>0</truncated>
		<difficult>0</difficult>
		<bndbox>
			<xmin>1703</xmin>
			<ymin>439</ymin>
			<xmax>1761</xmax>
			<ymax>483</ymax>
		</bndbox>
	</object>
	<object>
		<name>Plastic Bottle</name>
		<pose>Unspecified</pose>
		<truncated>0</truncated>
		<difficult>0</difficult>
		<bndbox>
			<xmin>1772</xmin>
			<ymin>346</ymin>
			<xmax>1840</xmax>
			<ymax>437</ymax>
		</bndbox>
	</object>
	<object>
		<name>Plastic Bottle</name>
		<pose>Unspecified</pose>
		<truncated>0</truncated>
		<difficult>0</difficult>
		<bndbox>
			<xmin>1750</xmin>
			<ymin>923</ymin>
			<xmax>1820</xmax>
			<ymax>999</ymax>
		</bndbox>
	</object>
	<object>
		<name>Plastic Bottle</name>
		<pose>Unspecified</pose>
		<truncated>0</truncated>
		<difficult>0</difficult>
		<bndbox>
			<xmin>2006</xmin>
			<ymin>849</ymin>
			<xmax>2106</xmax>
			<ymax>965</ymax>
		</bndbox>
	</object>
</annotation>
