<annotation verified="yes">
	<folder>029-nepal, Kathmandu-march12-sagar</folder>
	<filename>IMG_20200312_131510.jpg</filename>
	<path>/029-nepal, Kathmandu-march12-sagar/IMG_20200312_131510.jpg</path>
	<source>
		<database>Unknown</database>
	</source>
	<size>
		<width>3024</width>
		<height>4032</height>
		<depth>3</depth>
	</size>
	<segmented>0</segmented>
	<object>
		<name>Plastic Bottle</name>
		<pose>Unspecified</pose>
		<truncated>0</truncated>
		<difficult>0</difficult>
		<bndbox>
			<xmin>1266</xmin>
			<ymin>2564</ymin>
			<xmax>1320</xmax>
			<ymax>2613</ymax>
		</bndbox>
	</object>
	<object>
		<name>Plastic Bottle</name>
		<pose>Unspecified</pose>
		<truncated>0</truncated>
		<difficult>0</difficult>
		<bndbox>
			<xmin>1256</xmin>
			<ymin>2522</ymin>
			<xmax>1329</xmax>
			<ymax>2552</ymax>
		</bndbox>
	</object>
	<object>
		<name>Plastic Bottle</name>
		<pose>Unspecified</pose>
		<truncated>0</truncated>
		<difficult>0</difficult>
		<bndbox>
			<xmin>1511</xmin>
			<ymin>2691</ymin>
			<xmax>1568</xmax>
			<ymax>2775</ymax>
		</bndbox>
	</object>
</annotation>
