<annotation verified="yes">
	<folder>020-Zenica, Bosnia-March3rd-zerina</folder>
	<filename>IMG_20200303_162309.jpg</filename>
	<path>/020-Zenica, Bosnia-March3rd-zerina/IMG_20200303_162309.jpg</path>
	<source>
		<database>Unknown</database>
	</source>
	<size>
		<width>2240</width>
		<height>4000</height>
		<depth>3</depth>
	</size>
	<segmented>0</segmented>
	<object>
		<name>Plastic Bottle</name>
		<pose>Unspecified</pose>
		<truncated>0</truncated>
		<difficult>0</difficult>
		<bndbox>
			<xmin>631</xmin>
			<ymin>1618</ymin>
			<xmax>643</xmax>
			<ymax>1624</ymax>
		</bndbox>
	</object>
	<object>
		<name>Plastic Bottle</name>
		<pose>Unspecified</pose>
		<truncated>0</truncated>
		<difficult>0</difficult>
		<bndbox>
			<xmin>1027</xmin>
			<ymin>1708</ymin>
			<xmax>1037</xmax>
			<ymax>1712</ymax>
		</bndbox>
	</object>
	<object>
		<name>Plastic Bottle</name>
		<pose>Unspecified</pose>
		<truncated>0</truncated>
		<difficult>0</difficult>
		<bndbox>
			<xmin>1055</xmin>
			<ymin>1571</ymin>
			<xmax>1065</xmax>
			<ymax>1576</ymax>
		</bndbox>
	</object>
	<object>
		<name>Plastic Bottle</name>
		<pose>Unspecified</pose>
		<truncated>0</truncated>
		<difficult>0</difficult>
		<bndbox>
			<xmin>2090</xmin>
			<ymin>1579</ymin>
			<xmax>2103</xmax>
			<ymax>1585</ymax>
		</bndbox>
	</object>
	<object>
		<name>Plastic Bottle</name>
		<pose>Unspecified</pose>
		<truncated>0</truncated>
		<difficult>0</difficult>
		<bndbox>
			<xmin>2052</xmin>
			<ymin>1705</ymin>
			<xmax>2066</xmax>
			<ymax>1711</ymax>
		</bndbox>
	</object>
	<object>
		<name>Plastic Bottle</name>
		<pose>Unspecified</pose>
		<truncated>0</truncated>
		<difficult>0</difficult>
		<bndbox>
			<xmin>2191</xmin>
			<ymin>1575</ymin>
			<xmax>2203</xmax>
			<ymax>1581</ymax>
		</bndbox>
	</object>
	<object>
		<name>Plastic Bottle</name>
		<pose>Unspecified</pose>
		<truncated>0</truncated>
		<difficult>0</difficult>
		<bndbox>
			<xmin>2043</xmin>
			<ymin>1929</ymin>
			<xmax>2059</xmax>
			<ymax>1935</ymax>
		</bndbox>
	</object>
	<object>
		<name>Plastic Bottle</name>
		<pose>Unspecified</pose>
		<truncated>0</truncated>
		<difficult>0</difficult>
		<bndbox>
			<xmin>551</xmin>
			<ymin>2103</ymin>
			<xmax>582</xmax>
			<ymax>2112</ymax>
		</bndbox>
	</object>
</annotation>
